ipsocgen/__init__.py
ipsocgen/ipsocgen_cli.py
ipsocgen/common/__init__.py
ipsocgen/common/constants.py
ipsocgen/common/generate.py
ipsocgen/common/modules.py
ipsocgen/common/validate.py
ipsocgen/common/version.py
ipsocgen/common/schemas/schema_config.yaml
ipsocgen/common/schemas/schema_master.yaml
ipsocgen/common/schemas/schema_slave.yaml
ipsocgen/common/templates/axi4_crossbar.txt
ipsocgen/common/templates/axi4_custom_master.txt
ipsocgen/common/templates/axi4_custom_slave.txt
ipsocgen/common/templates/axi4_dma.txt
ipsocgen/common/templates/axi4_ethernet.txt
ipsocgen/common/templates/axi4_irq_ctrl.txt
ipsocgen/common/templates/axi4_mem_ram.txt
ipsocgen/common/templates/axi4_mem_rom.txt
ipsocgen/common/templates/axi4_rst_ctrl.txt
ipsocgen/common/templates/axi4_timer.txt
ipsocgen/common/templates/axi4_uart.txt
ipsocgen/common/templates/clk_basic.txt
ipsocgen/common/templates/clk_pll_xilinx.txt
ipsocgen/common/templates/clk_simple.txt
ipsocgen/common/templates/module_defines.txt
ipsocgen/common/templates/module_header.txt
ipsocgen/common/templates/module_instance.txt
ipsocgen/common/templates/nox_wrapper.txt
ipsocgen/common/templates/ravenoc.txt
ipsocgen/common/templates/rst_simple.txt
ipsocgen/common/templates/vex_wrapper.txt
ipsocgen-0.1.39.dist-info/LICENSE
ipsocgen-0.1.39.dist-info/METADATA
ipsocgen-0.1.39.dist-info/WHEEL
ipsocgen-0.1.39.dist-info/entry_points.txt
ipsocgen-0.1.39.dist-info/top_level.txt
ipsocgen-0.1.39.dist-info/RECORD
