Metadata-Version: 2.1
Name: ipsocgen
Version: 0.1.39
Summary: Generic SoC builder in HDL
Home-page: https://github.com/aignacio/ipsocgen
Author: aignacio (Anderson Ignacio)
Author-email: <anderson@aignacio.com>
Keywords: soc,mpsoc,hdl,verilog,systemverilog,builder
Classifier: Development Status :: 1 - Planning
Classifier: Intended Audience :: Developers
Classifier: Programming Language :: Python :: 3
Classifier: License :: OSI Approved :: MIT License
Classifier: Operating System :: Unix
Classifier: Operating System :: MacOS :: MacOS X
Classifier: Operating System :: Microsoft :: Windows
License-File: LICENSE
Requires-Dist: tabulate
Requires-Dist: argparse
Requires-Dist: pyyaml
Requires-Dist: cerberus
Requires-Dist: jinja2
